temporis-1.0.7.dist-info/METADATA
temporis-1.0.7.dist-info/WHEEL
temporis-1.0.7.dist-info/entry_points.txt
temporis-1.0.7.dist-info/licenses/LICENSE
temporis/__init__.py
temporis/format.py
temporis/references.py
temporis/temporis.py
temporis/timezone.py
temporis/zones.py
temporis-1.0.7.dist-info/RECORD
