Metadata-Version: 2.1
Name: temporis
Version: 1.0.7
Summary: Temporis is a Python library for elegantly managing and transforming dates and times. It provides intuitive tools for handling temporal data, making time calculations, conversions, and formatting simple and efficient.
Author-Email: Jancel <ja.alvarezgom@gmail.com>
License: MIT
Classifier: Programming Language :: Python :: 3.10
Classifier: Programming Language :: Python :: 3.11
Classifier: Programming Language :: Python :: 3.12
Classifier: Development Status :: 5 - Production/Stable
Classifier: Topic :: Software Development :: Libraries :: Python Modules
Classifier: Topic :: Software Development :: Libraries :: Application Frameworks
Classifier: Topic :: Software Development :: Libraries
Classifier: Topic :: Software Development
Classifier: Topic :: Utilities
Classifier: Typing :: Typed
Project-URL: Homepage, https://github.com/jalvarezgom/temporis
Project-URL: Issues, https://github.com/jalvarezgom/temporis/issues
Requires-Python: >=3.10
Requires-Dist: tzdata>=2024.1
Requires-Dist: python-dateutil>=2.9.0.post0
Requires-Dist: pytz>=2025.2
